odoo9_addon_mass_editing-9.0.1.0.0-py2.7-nspkg.pth
odoo9_addon_mass_editing-9.0.1.0.0.dist-info/top_level.txt
odoo9_addon_mass_editing-9.0.1.0.0.dist-info/WHEEL
odoo9_addon_mass_editing-9.0.1.0.0.dist-info/RECORD
odoo9_addon_mass_editing-9.0.1.0.0.dist-info/metadata.json
odoo9_addon_mass_editing-9.0.1.0.0.dist-info/DESCRIPTION.rst
odoo9_addon_mass_editing-9.0.1.0.0.dist-info/METADATA
odoo9_addon_mass_editing-9.0.1.0.0.dist-info/namespace_packages.txt
odoo_addons/mass_editing/__openerp__.py
odoo_addons/mass_editing/hooks.py
odoo_addons/mass_editing/ChangeLog.txt
odoo_addons/mass_editing/__init__.py
odoo_addons/mass_editing/README.rst
odoo_addons/mass_editing/security/ir.model.access.csv
odoo_addons/mass_editing/models/mass_object.py
odoo_addons/mass_editing/models/__init__.py
odoo_addons/mass_editing/models/ir_model_fields.py
odoo_addons/mass_editing/i18n/ru.po
odoo_addons/mass_editing/i18n/it.po
odoo_addons/mass_editing/i18n/es.po
odoo_addons/mass_editing/i18n/fr_CA.po
odoo_addons/mass_editing/i18n/sl.po
odoo_addons/mass_editing/i18n/de.po
odoo_addons/mass_editing/i18n/mass_editing.pot
odoo_addons/mass_editing/i18n/fr.po
odoo_addons/mass_editing/i18n/pt_BR.po
odoo_addons/mass_editing/wizard/__init__.py
odoo_addons/mass_editing/wizard/mass_editing_wizard.py
odoo_addons/mass_editing/views/mass_editing_view.xml
odoo_addons/mass_editing/tests/__init__.py
odoo_addons/mass_editing/tests/test_mass_editing.py
odoo_addons/mass_editing/static/description/mass_editing-2.png
odoo_addons/mass_editing/static/description/mass_editing-5.png
odoo_addons/mass_editing/static/description/mass_editing-3.png
odoo_addons/mass_editing/static/description/mass_editing-1.png
odoo_addons/mass_editing/static/description/mass_editing-4.png
odoo_addons/mass_editing/static/description/icon.png
